{
  "tours": [
    {
      "id": 1,
      "name": "Tour Hà Nội 3 Ngày 2 Đêm",
      "location": "Hà Nội",
      "description": "Khám phá vẻ đẹp thủ đô với tour du lịch 3 ngày 2 đêm.",
      "price": "3,500,000 VND",
      "image": "/assets/images/tour1.jpeg",
      "type": "domestic",
      "isBestSelling": true
    },
    {
      "id": 2,
      "name": "Tour Sài Gòn 4 Ngày 3 Đêm",
      "location": "Sài Gòn",
      "description": "Khám phá thành phố Sài Gòn sôi động với tour 4 ngày 3 đêm.",
      "price": "4,200,000 VND",
      "image": "/assets/images/tour2.jpeg",
      "type": "domestic",
      "isBestSelling": true
    },
    {
      "id": 3,
      "name": "Tour Đà Nẵng 3 Ngày 2 Đêm",
      "location": "Đà Nẵng",
      "description": "Khám phá thành phố biển Đà Nẵng xinh đẹp trong 3 ngày.",
      "price": "3,800,000 VND",
      "image": "/assets/images/tour3.jpeg",
      "type": "domestic",
      "isBestSelling": true
    },
    {
      "id": 4,
      "name": "Tour Pháp 7 Ngày 6 Đêm",
      "location": "Paris",
      "description": "Khám phá Paris và những thành phố nổi tiếng khác tại Pháp.",
      "price": "10,000,000 VND",
      "image": "/assets/images/tour1.jpeg",
      "type": "international",
      "isBestSelling": true
    },
    {
      "id": 5,
      "name": "Tour Nhật Bản 6 Ngày 5 Đêm",
      "location": "Tokyo",
      "description": "Khám phá Tokyo và các thành phố nổi tiếng khác ở Nhật Bản.",
      "price": "12,000,000 VND",
      "image": "/assets/images/tour1.jpeg",
      "type": "international",
      "isBestSelling": false
    },
    {
      "id": 6,
      "name": "Tour Bali 5 Ngày 4 Đêm",
      "location": "Bali",
      "description": "Khám phá vẻ đẹp của Bali, hòn đảo thiên đường của Indonesia.",
      "price": "8,500,000 VND",
      "image": "/assets/images/tour2.jpeg",
      "type": "international",
      "isBestSelling": true
    },
    {
      "id": 7,
      "name": "Tour Côn Đảo 3 Ngày 2 Đêm",
      "location": "Côn Đảo",
      "description": "Khám phá lịch sử và thiên nhiên của Côn Đảo.",
      "price": "5,000,000 VND",
      "image": "/assets/images/tour3.jpeg",
      "type": "domestic",
      "isBestSelling": true
    },
    {
      "id": 8,
      "name": "Tour Mỹ 10 Ngày 9 Đêm",
      "location": "New York",
      "description": "Khám phá các thành phố lớn của Mỹ, từ New York đến Los Angeles.",
      "price": "20,000,000 VND",
      "image": "/assets/images/tour2.jpeg",
      "type": "international",
      "isBestSelling": false
    },
    {
      "id": 9,
      "name": "Tour Hong Kong 4 Ngày 3 Đêm",
      "location": "Hong Kong",
      "description": "Khám phá Hong Kong, một trong những thành phố sôi động nhất châu Á.",
      "price": "6,000,000 VND",
      "image": "/assets/images/tour1.jpeg",
      "type": "international",
      "isBestSelling": true
    },
    {
      "id": 10,
      "name": "Tour Hạ Long 2 Ngày 1 Đêm",
      "location": "Hạ Long",
      "description": "Khám phá Vịnh Hạ Long với các tour thuyền trên vịnh.",
      "price": "2,500,000 VND",
      "image": "/assets/images/tour2.jpeg",
      "type": "domestic",
      "isBestSelling": true
    }
  ]
}
